tmenu/__init__.py
tmenu/tmenu.py
senttelegrammenu-1.0.0.dist-info/LICENSE
senttelegrammenu-1.0.0.dist-info/METADATA
senttelegrammenu-1.0.0.dist-info/WHEEL
senttelegrammenu-1.0.0.dist-info/top_level.txt
senttelegrammenu-1.0.0.dist-info/RECORD
