Metadata-Version: 2.1
Name: senttelegrammenu
Version: 1.0.0
Summary: Superstructure over telebot which can show inline keyboard telegram menu
Home-page: https://github.com/Senteris/SentTelegramMenu
Author: Senteris
Author-email: senteristeam@gmail.com
License: UNKNOWN
Platform: UNKNOWN
Classifier: Programming Language :: Python :: 3
Classifier: License :: OSI Approved :: GNU General Public License v3 (GPLv3)
Classifier: Operating System :: OS Independent
Requires-Python: >=3.6
Requires-Dist: pytelegrambotapi
